ansys/tools/protoc_helper/__init__.py
ansys/tools/protoc_helper/_compile_protos.py
ansys/tools/protoc_helper/_distutils_overrides.py
ansys/tools/protoc_helper/py.typed
ansys_tools_protoc_helper-0.5.0.dist-info/entry_points.txt
ansys_tools_protoc_helper-0.5.0.dist-info/LICENSE
ansys_tools_protoc_helper-0.5.0.dist-info/WHEEL
ansys_tools_protoc_helper-0.5.0.dist-info/METADATA
ansys_tools_protoc_helper-0.5.0.dist-info/RECORD
