Metadata-Version: 2.1
Name: ansys-tools-protoc-helper
Version: 0.5.0
Summary: A utility for compiling '.proto' files to Python source.
Author: ANSYS, Inc.
Maintainer-email: PyAnsys developers <pyansys.support@ansys.com>
Requires-Python: >=3.9,<3.12
Classifier: License :: OSI Approved :: MIT License
Requires-Dist: setuptools>=42.0
Requires-Dist: grpcio-tools==1.49.1
Requires-Dist: protobuf==4.21.12
Requires-Dist: mypy-protobuf==3.1.0
Requires-Dist: importlib-resources>=1.3
Requires-Dist: sphinx ; extra == "doc"
Requires-Dist: numpydoc ; extra == "doc"
Requires-Dist: ansys-sphinx-theme ; extra == "doc"
Requires-Dist: sphinx-copybutton ; extra == "doc"
Requires-Dist: pre-commit~=2.16.0 ; extra == "pre-commit"
Requires-Dist: mypy==0.931 ; extra == "pre-commit"
Requires-Dist: types-setuptools==57.4.7 ; extra == "pre-commit"
Requires-Dist: pytest~=6.0 ; extra == "test"
Project-URL: Source, https://github.com/ansys/ansys-tools-protoc-helper
Provides-Extra: doc
Provides-Extra: pre-commit
Provides-Extra: test
